[
  {
    "@id": "_:n3-996",
    "https://prez.dev/currentProfile": [
      {
        "@id": "https://prez.dev/OGCSchemesObjectProfile"
      }
    ]
  },
  {
    "@id": "https://linked.data.gov.au/catalogue/gswa-vocabs",
    "https://prez.dev/identifier": [
      {
        "@value": "catalogue:gswa-vocabs"
      }
    ]
  },
  {
    "@id": "https://linked.data.gov.au/def/vertical-depth-reference-systems",
    "https://prez.dev/identifier": [
      {
        "@value": "ns1:vertical-depth-reference-systems"
      }
    ],
    "https://prez.dev/link": [
      {
        "@value": "/catalogs/catalogue:gswa-vocabs/collections/ns1:vertical-depth-reference-systems"
      }
    ],
    "https://prez.dev/label": [
      {
        "@value": "Vertical/depth reference systems",
        "@language": "en"
      }
    ],
    "https://prez.dev/description": [
      {
        "@value": "The point or level from which heights and depths are measured and referenced to for an entity or activity. Typically these are expressed relative to a common global or regional reference datum such as the Australian Height Datum (AHD) or can be related to local reference systems. Specific emphasis is placed on elevation references used by resource exploration and drilling programs, whereby depths are measured relative to local reference datums or specific parts of a borehole/drilling platform. Concepts in this vocabulary include both reference datums (e.g. mean sea level) and how depths are expressed relative to them (e.g. mean sea level height).",
        "@language": "en"
      }
    ],
    "https://prez.dev/members": [
      {
        "@value": "/catalogs/catalogue:gswa-vocabs/collections/ns1:vertical-depth-reference-systems/items"
      }
    ]
  },
  {
    "@id": "https://linked.data.gov.au/def/vertical-depth-reference-systems/rotary-table",
    "@type": [
      "http://www.w3.org/2004/02/skos/core#Concept"
    ],
    "https://schema.org/citation": [
      {
        "@value": "https://linked.data.gov.au/def/depth-reference/rotary-table",
        "@type": "http://www.w3.org/2001/XMLSchema#anyURI"
      },
      {
        "@value": "https://glossary.slb.com/en/terms/r/rotary_table",
        "@type": "http://www.w3.org/2001/XMLSchema#anyURI"
      }
    ],
    "http://www.w3.org/2000/01/rdf-schema#isDefinedBy": [
      {
        "@id": "https://linked.data.gov.au/def/vertical-depth-reference-systems"
      }
    ],
    "http://www.w3.org/2004/02/skos/core#altLabel": [
      {
        "@value": "BRT",
        "@language": "en"
      },
      {
        "@value": "RT",
        "@language": "en"
      }
    ],
    "http://www.w3.org/2004/02/skos/core#definition": [
      {
        "@value": "The revolving or spinning section of the drill floor that provides power to turn the drillstring in a clockwise direction (as viewed from above), often used as a starting point for measurement of borehole depth (below rotary table or BRT).",
        "@language": "en"
      }
    ],
    "http://www.w3.org/2004/02/skos/core#historyNote": [
      {
        "@value": "Energy industry concept"
      }
    ],
    "http://www.w3.org/2004/02/skos/core#inScheme": [
      {
        "@id": "https://linked.data.gov.au/def/vertical-depth-reference-systems"
      }
    ],
    "http://www.w3.org/2004/02/skos/core#prefLabel": [
      {
        "@value": "rotary table",
        "@language": "en"
      }
    ],
    "http://www.w3.org/2004/02/skos/core#closeMatch": [
      {
        "@id": "https://linked.data.gov.au/def/depth-reference/rotary-table"
      }
    ],
    "https://prez.dev/identifier": [
      {
        "@value": "ns1:rotary-table"
      }
    ],
    "https://prez.dev/link": [
      {
        "@value": "/catalogs/catalogue:gswa-vocabs/collections/ns1:vertical-depth-reference-systems/items/ns1:rotary-table"
      }
    ],
    "https://prez.dev/type": [
      {
        "@id": "https://prez.dev/FocusNode"
      }
    ],
    "https://prez.dev/label": [
      {
        "@value": "rotary table",
        "@language": "en"
      }
    ],
    "https://prez.dev/description": [
      {
        "@value": "The revolving or spinning section of the drill floor that provides power to turn the drillstring in a clockwise direction (as viewed from above), often used as a starting point for measurement of borehole depth (below rotary table or BRT).",
        "@language": "en"
      }
    ]
  },
  {
    "@id": "https://prez.dev/link",
    "https://prez.dev/label": [
      {
        "@value": "link"
      }
    ]
  },
  {
    "@id": "https://prez.dev/members",
    "https://prez.dev/label": [
      {
        "@value": "members"
      }
    ]
  }
]