{"@context":{"iri":"@id","prefLabel":"http://www.w3.org/2004/02/skos/core#prefLabel","definition":"http://www.w3.org/2004/02/skos/core#definition","members":"http://www.w3.org/2004/02/skos/core#member"},"@graph":[{"iri":"https://linked.data.gov.au/def/mass-brands","prefLabel":"Mass brands","members":["http://pid.suncorp.com.au/def/brand/aami","http://pid.suncorp.com.au/def/brand/gio","http://pid.suncorp.com.au/def/brand/suncorp","http://pid.suncorp.com.au/def/brand/apia"],"definition":"Suncorp mass brands."},{"iri":"https://linked.data.gov.au/def/nz-brands","prefLabel":"New Zealand brands","members":["http://pid.suncorp.com.au/def/brand/aainz"],"definition":"New Zealand brands."}]}