{
  "vocabularies": [
    {
      "iri": "https://example.org/vocab/colors/scheme",
      "slug": "example-colors",
      "prefLabel": "Example Colors",
      "definition": "A sample vocabulary demonstrating prez-lite. Replace with your own vocabularies.",
      "conceptCount": 8,
      "topConcepts": [
        "https://example.org/vocab/colors/primary",
        "https://example.org/vocab/colors/secondary"
      ],
      "modified": "2025-01-01",
      "created": "2025-01-01",
      "version": null,
      "versionIRI": null,
      "status": null,
      "statusLabel": null,
      "publisher": [],
      "publisherLabels": [],
      "creator": [],
      "creatorLabels": [],
      "themes": [],
      "themeLabels": [],
      "formats": [
        "ttl",
        "json",
        "jsonld",
        "rdf",
        "csv",
        "html"
      ]
    }
  ]
}